HomeBattery/__init__.py
HomeBattery/battery.py
HomeBattery/modbus.py
HomeBattery/batteries/deye_modbus.py
HomeBattery/batteries/deye_solarman.py
HomeBattery/batteries/sessy.py
HomeBattery/batteries/sigenergy.py
HomeBattery/batteries/sma.py
HomeBattery/batteries/sun2000.py
HomeBattery/batteries/victron.py
homebattery-0.0.13.dist-info/licenses/LICENSE
homebattery-0.0.13.dist-info/METADATA
homebattery-0.0.13.dist-info/WHEEL
homebattery-0.0.13.dist-info/top_level.txt
homebattery-0.0.13.dist-info/RECORD
