Metadata-Version: 2.4
Name: HomeBattery
Version: 0.0.13
Summary: Simplified communication with home batteries
Author-email: Joost van Andel <joost.van.andel@elaad.nl>, Ton Smets <ton.smets@elaad.nl>, ElaadNL <info@elaad.nl>
License:                     GNU GENERAL PUBLIC LICENSE
Project-URL: Homepage, https://github.com/ElaadNL/HomeBattery
Project-URL: Issues, https://github.com/ElaadNL/HomeBattery/issues
Classifier: Programming Language :: Python :: 3
Classifier: Operating System :: OS Independent
Requires-Python: >=3.8
License-File: LICENSE
Requires-Dist: aiohttp==3.11.9
Requires-Dist: pymodbus==3.7.2
Requires-Dist: pysolarmanv5==3.0.6
Dynamic: license-file
